<?xml version="1.0" encoding="utf-8"?>
<savedqueries>
  <savedquery>
    <IsCustomizable>1</IsCustomizable>
    <CanBeDeleted>0</CanBeDeleted>
    <isquickfindquery>0</isquickfindquery>
    <isprivate>0</isprivate>
    <isdefault>1</isdefault>
    <savedqueryid>{510bd4fb-5213-491f-9a41-65b65f56acf8}</savedqueryid>
    <layoutxml>
      <grid name="resultset" jump="ccllc_name" select="1" icon="1" preview="1">
        <row name="result" id="ccllc_feeid">
          <cell name="ccllc_name" width="300" />
          <cell name="createdon" width="125" />
        </row>
      </grid>
    </layoutxml>
    <querytype>0</querytype>
    <fetchxml>
      <fetch version="1.0" mapping="logical">
        <entity name="ccllc_fee">
          <attribute name="ccllc_feeid" />
          <attribute name="ccllc_name" />
          <attribute name="createdon" />
          <order attribute="ccllc_name" descending="false" />
          <filter type="and">
            <condition attribute="statecode" operator="eq" value="0" />
          </filter>
        </entity>
      </fetch>
    </fetchxml>
    <IntroducedVersion>0.0.0.0</IntroducedVersion>
    <LocalizedNames>
      <LocalizedName description="Active Fees" languagecode="1033" />
    </LocalizedNames>
  </savedquery>
</savedqueries>